rest_framework_custom_exceptions/__init__.py
rest_framework_custom_exceptions/exceptions.py
tests/__init__.py
tests/models.py
tests/serializers.py
tests/test_serializers.py
tests/urls.py
tests/views.py
djangorestframework_custom_exceptions-1.0.2.dist-info/LICENSE
djangorestframework_custom_exceptions-1.0.2.dist-info/METADATA
djangorestframework_custom_exceptions-1.0.2.dist-info/WHEEL
djangorestframework_custom_exceptions-1.0.2.dist-info/top_level.txt
djangorestframework_custom_exceptions-1.0.2.dist-info/RECORD
