Metadata-Version: 1.2
Name: djangorestframework-custom-exceptions
Version: 1.0.2
Summary: Custom exceptions for Django REST Framework
Home-page: https://github.com/unistra/django-rest-framework-custom-exceptions
Author: Morgan Bohn
Author-email: morgan.bohn@unistra.fr
Maintainer: Morgan Bohn
Maintainer-email: morgan.bohn@unistra.fr
License: UNKNOWN
Download-URL: https://pypi.python.org/pypi/djangorestframework-custom-exceptions
Keywords: django,REST,rest_framework,exceptions
Platform: UNKNOWN
Classifier: Development Status :: 4 - Beta
Classifier: Environment :: Web Environment
Classifier: Framework :: Django
Classifier: Intended Audience :: Developers
Classifier: License :: OSI Approved :: GNU General Public License v2 (GPLv2)
Classifier: Programming Language :: Python :: 2.7
Classifier: Programming Language :: Python :: 3
